onnx_passes/__init__.py
onnx_passes/__main__.py
onnx_passes/ops/__init__.py
onnx_passes/ops/qonnx.py
onnx_passes/ops/thresholds.py
onnx_passes/passes/__init__.py
onnx_passes/passes/analysis/__init__.py
onnx_passes/passes/analysis/checker.py
onnx_passes/passes/annotation/__init__.py
onnx_passes/passes/annotation/shapes.py
onnx_passes/passes/base.py
onnx_passes/passes/cleanup/__init__.py
onnx_passes/passes/cleanup/constants.py
onnx_passes/passes/cleanup/names.py
onnx_passes/passes/cleanup/remove.py
onnx_passes/passes/cleanup/sort.py
onnx_passes/passes/compose.py
onnx_passes/passes/constants.py
onnx_passes/passes/convert.py
onnx_passes/passes/eliminate/__init__.py
onnx_passes/passes/eliminate/constants.py
onnx_passes/passes/fusion/__init__.py
onnx_passes/passes/fusion/thresholds.py
onnx_passes/passes/imports/__init__.py
onnx_passes/passes/imports/qonnx.py
onnx_passes/passes/inline/__init__.py
onnx_passes/passes/inline/batchnorm.py
onnx_passes/passes/inline/functions.py
onnx_passes/passes/inline/qonnx.py
onnx_passes/passes/inline/thresholds.py
onnx_passes/passes/runtime.py
onnx_passes/passes/streamline/__init__.py
onnx_passes/passes/streamline/algebraic/__init__.py
onnx_passes/passes/streamline/algebraic/_properties.py
onnx_passes/passes/streamline/algebraic/bitwise.py
onnx_passes/passes/streamline/algebraic/boolean.py
onnx_passes/passes/streamline/algebraic/matmul.py
onnx_passes/passes/streamline/algebraic/numeric.py
onnx_passes/passes/streamline/shapes.py
onnx_passes/passes/streamline/transpose.py
onnx_passes/passes/util.py
onnx_passes/passes/verify.py
onnx_passes/traits/__init__.py
onnx_passes/traits/elementwise.py
onnx_passes-0.3.0.dist-info/LICENSE
onnx_passes-0.3.0.dist-info/METADATA
onnx_passes-0.3.0.dist-info/WHEEL
onnx_passes-0.3.0.dist-info/entry_points.txt
onnx_passes-0.3.0.dist-info/RECORD
